bundle_placement-0.0.1.dist-info/DESCRIPTION.rst
bundle_placement-0.0.1.dist-info/METADATA
bundle_placement-0.0.1.dist-info/RECORD
bundle_placement-0.0.1.dist-info/WHEEL
bundle_placement-0.0.1.dist-info/entry_points.txt
bundle_placement-0.0.1.dist-info/metadata.json
bundle_placement-0.0.1.dist-info/top_level.txt
bundleplacer/__init__.py
bundleplacer/__main__.py
bundleplacer/assignmenttype.py
bundleplacer/async.py
bundleplacer/bundle.py
bundleplacer/charmstore_api.py
bundleplacer/cli.py
bundleplacer/config.py
bundleplacer/consts.py
bundleplacer/controller.py
bundleplacer/grapher.py
bundleplacer/log.py
bundleplacer/maas.py
bundleplacer/machine.py
bundleplacer/placerview.py
bundleplacer/relationtype.py
bundleplacer/service.py
bundleplacer/state.py
bundleplacer/tarjan.py
bundleplacer/utils.py
bundleplacer/fixtures/__init__.py
bundleplacer/fixtures/maas.py
bundleplacer/ui/__init__.py
bundleplacer/ui/charmstore.py
bundleplacer/ui/filter_box.py
bundleplacer/ui/machines_column.py
bundleplacer/ui/machines_list.py
bundleplacer/ui/options_column.py
bundleplacer/ui/relations_column.py
bundleplacer/ui/services_column.py
bundleplacer/ui/services_list.py
bundleplacer/ui/simple_machine_widget.py
bundleplacer/ui/simple_service_widget.py
