Metadata-Version: 2.0
Name: bundle-placement
Version: 0.0.1
Summary: Juju bundle placer
Home-page: https://github.com/ubuntu-solutions-engineering/bundle-placement
Author: Mike McCracken
Author-email: mike.mccracken@ubuntu.com
License: UNKNOWN
Platform: UNKNOWN
